pytorch_wavelet/__init__.py
pytorch_wavelet/pytorch_wavelet.py
pytorch_wavelet-1.2.dist-info/METADATA
pytorch_wavelet-1.2.dist-info/WHEEL
pytorch_wavelet-1.2.dist-info/top_level.txt
pytorch_wavelet-1.2.dist-info/RECORD
